nuflow/__init__.py
nuflow-0.0.1.dist-info/METADATA
nuflow-0.0.1.dist-info/WHEEL
nuflow-0.0.1.dist-info/RECORD
