Metadata-Version: 2.4
Name: nuflow
Version: 0.0.1
Summary: NuFlow — Multimodal AI orchestration.
Project-URL: Homepage, https://github.com/NuFlowIO/nuflow
Project-URL: Issues, https://github.com/NuFlowIO/nuflow/issues
Author-email: ram <ram@nuflow.io>
License: MIT
Keywords: ai,audio,dag,multimodal,orchestration,video
Classifier: Development Status :: 3 - Alpha
Classifier: Intended Audience :: Developers
Classifier: License :: OSI Approved :: MIT License
Classifier: Operating System :: OS Independent
Classifier: Programming Language :: Python :: 3
Classifier: Topic :: Software Development :: Libraries
Requires-Python: >=3.9
